metaflow_extensions/sentry/config/metaflow_config.py
metaflow_extensions/sentry/config/mfextinit_sentry.py
metaflow_extensions/sentry/plugins/mfextinit_sentry.py
metaflow_extensions/sentry/plugins/sentry_logging_step_decorator.py
metaflow_extensions/sentry/toplevel/mfextinit_sentry.py
metaflow_extensions/sentry/toplevel/sentry_toplevel.py
metaflow_sentry_logger-0.2.1.dist-info/METADATA
metaflow_sentry_logger-0.2.1.dist-info/WHEEL
metaflow_sentry_logger-0.2.1.dist-info/entry_points.txt
metaflow_sentry_logger-0.2.1.dist-info/top_level.txt
metaflow_sentry_logger-0.2.1.dist-info/RECORD
