Metadata-Version: 2.1
Name: metaflow-sentry-logger
Version: 0.2.1
Summary: Sentry logging plugins for Metaflow (metaflow.org)
Author: Richard Smith
Project-URL: Homepage, https://github.com/rsmith013/metaflow-sentry-logger
Keywords: metaflow
Classifier: License :: OSI Approved :: MIT License
Classifier: Programming Language :: Python
Classifier: Programming Language :: Python :: 3
Requires-Python: >=3.7
Requires-Dist: sentry-sdk
Requires-Dist: metaflow
Provides-Extra: dev
Requires-Dist: pip-tools ; extra == 'dev'
Requires-Dist: pytest ; extra == 'dev'
Requires-Dist: bumpver ; extra == 'dev'
Requires-Dist: pre-commit ; extra == 'dev'
